Pythpack/__init__.py
Pythpack/mod_pack.py
Pythpack/first_pack/__init__.py
Pythpack/first_pack/name1.py
Pythpack/first_pack/name2.py
Pythpack/second_pack/__init__.py
Pythpack/second_pack/name3.py
Pythpack/second_pack/name4.py
Pythpack-0.1.dist-info/LICENSE.txt
Pythpack-0.1.dist-info/METADATA
Pythpack-0.1.dist-info/WHEEL
Pythpack-0.1.dist-info/top_level.txt
Pythpack-0.1.dist-info/RECORD
