Metadata-Version: 2.1
Name: Pythpack
Version: 0.1
Summary: Let's start
Home-page: UNKNOWN
Author: varun9816
Author-email: varunsvr98@outlook.com
License: UNKNOWN
Platform: UNKNOWN
Classifier: Programming Language :: Python :: 3
Classifier: License :: OSI Approved :: MIT License
Classifier: Operating System :: OS Independent
License-File: LICENSE.txt
